trainerlog/__init__.py
trainerlog/trainlog.py
trainerlog-0.4.0.dist-info/METADATA
trainerlog-0.4.0.dist-info/WHEEL
trainerlog-0.4.0.dist-info/RECORD
