Metadata-Version: 2.1
Name: trainerlog
Version: 0.4.0
Summary: Nice colorful log with TRAIN level too
Home-page: https://gitlab.com/ninpnin/trainlog
License: MIT
Author: ninpnin
Author-email: vainoyrjanainen@icloud.com
Requires-Python: >=3.7,<4.0
Classifier: License :: OSI Approved :: MIT License
Classifier: Programming Language :: Python :: 3
Classifier: Programming Language :: Python :: 3.7
Classifier: Programming Language :: Python :: 3.8
Classifier: Programming Language :: Python :: 3.9
Classifier: Programming Language :: Python :: 3.10
Classifier: Programming Language :: Python :: 3.11
Classifier: Programming Language :: Python :: 3.12
Requires-Dist: colorlog
Project-URL: Repository, https://gitlab.com/ninpnin/trainlog
